Metadata-Version: 2.1
Name: maxipago-sdk
Version: 1.0.4
Summary: SDK python
Home-page: https://github.com/tfedatto/sdk-python
Author: Stored
Author-email: contato@stored.com.br
License: MIT
Platform: UNKNOWN
Classifier: Topic :: Utilities
Requires-Dist: requests (==1.1.0)
Requires-Dist: lxml (==4.1.1)
